goldsberry/__init__.py
goldsberry/_apifunctions.py
goldsberry/apiconvertor.py
goldsberry/apiparams.py
goldsberry/masterclass.py
goldsberry/draft/_Draft.py
goldsberry/draft/_Draft2.py
goldsberry/draft/__init__.py
goldsberry/draft/draft.py
goldsberry/game/_Game.py
goldsberry/game/_Game2.py
goldsberry/game/__init__.py
goldsberry/game/game.py
goldsberry/league/_League.py
goldsberry/league/_League2.py
goldsberry/league/__init__.py
goldsberry/league/league.py
goldsberry/player/_Player.py
goldsberry/player/_Player2.py
goldsberry/player/__init__.py
goldsberry/player/player.py
goldsberry/playtype/_PlayType.py
goldsberry/playtype/_PlayType2.py
goldsberry/playtype/__init__.py
goldsberry/sportvu/_SportVu.py
goldsberry/sportvu/_SportVu2.py
goldsberry/sportvu/__init__.py
goldsberry/sportvu/sportvu.py
goldsberry/team/_Team.py
goldsberry/team/_Team2.py
goldsberry/team/__init__.py
py_goldsberry-1.1.dist-info/AUTHORS.rst
py_goldsberry-1.1.dist-info/LICENSE
py_goldsberry-1.1.dist-info/METADATA
py_goldsberry-1.1.dist-info/WHEEL
py_goldsberry-1.1.dist-info/top_level.txt
py_goldsberry-1.1.dist-info/RECORD
