Metadata-Version: 1.1
Name: py-goldsberry
Version: 1.1
Summary: API interface for stats.nba.com
Home-page: http://github.com/bradleyfay/py-goldsberry
Author: Bradley Fay
Author-email: bradley.fay@gmail.com
License: MIT
Keywords: sports NBA basketball
Platform: any
Classifier: Development Status :: 3 - Alpha
Classifier: License :: OSI Approved :: MIT License
Classifier: Programming Language :: Python :: 2
Classifier: Programming Language :: Python :: 2.6
Classifier: Programming Language :: Python :: 2.7
Classifier: Programming Language :: Python :: 3
